origo/__init__.py
origo/config.py
origo/exceptions.py
origo/file_cache.py
origo/io_utils.py
origo/sdk.py
origo/auth/__init__.py
origo/auth/auth.py
origo/auth/util.py
origo/auth/credentials/__init__.py
origo/auth/credentials/client_credentials.py
origo/auth/credentials/common.py
origo/auth/credentials/password_grant.py
origo/data/__init__.py
origo/data/dataset.py
origo/data/download.py
origo/data/upload.py
origo/dataset_authorizer/__init__.py
origo/dataset_authorizer/simple_dataset_authorizer_client.py
origo/elasticsearch/__init__.py
origo/elasticsearch/queries.py
origo/event/__init__.py
origo/event/event_stream_client.py
origo/event/post_event.py
origo/pipelines/__init__.py
origo/pipelines/client.py
origo/pipelines/resources/__init__.py
origo/pipelines/resources/pipeline.py
origo/pipelines/resources/pipeline_base.py
origo/pipelines/resources/pipeline_input.py
origo/pipelines/resources/pipeline_instance.py
origo/pipelines/resources/schema.py
origo/pipelines/resources/schemas/pipeline-inputs.json
origo/pipelines/resources/schemas/pipeline-instances.json
origo/pipelines/resources/schemas/pipelines.json
origo/pipelines/resources/schemas/schemas.json
origo/status/__init__.py
origo/status/status.py
origo_sdk_python-0.3.1.data/data/schema/pipeline-inputs.json
origo_sdk_python-0.3.1.data/data/schema/pipeline-instances.json
origo_sdk_python-0.3.1.data/data/schema/pipelines.json
origo_sdk_python-0.3.1.data/data/schema/schemas.json
origo_sdk_python-0.3.1.dist-info/LICENSE
origo_sdk_python-0.3.1.dist-info/METADATA
origo_sdk_python-0.3.1.dist-info/WHEEL
origo_sdk_python-0.3.1.dist-info/top_level.txt
origo_sdk_python-0.3.1.dist-info/RECORD
