Metadata-Version: 2.1
Name: origo-sdk-python
Version: 0.3.1
Summary: SDK for origo
Home-page: https://github.com/oslokommune/origo-sdk-python
Author: Oslo Origo
Author-email: dataplattform@oslo.kommune.no
License: UNKNOWN
Platform: UNKNOWN
Classifier: Development Status :: 3 - Alpha
Classifier: Programming Language :: Python :: 3
Classifier: License :: OSI Approved :: MIT License
Classifier: Operating System :: OS Independent
Requires-Python: >=3.6
Requires-Dist: PrettyTable
Requires-Dist: PyJWT
Requires-Dist: jsonschema
Requires-Dist: python-keycloak
Requires-Dist: requests
Requires-Dist: urllib3
